dataclass_collections/__init__.py
dataclass_collections/list_collection.py
dataclass_collections-0.1.3.dist-info/METADATA
dataclass_collections-0.1.3.dist-info/WHEEL
dataclass_collections-0.1.3.dist-info/RECORD
